adaptivecardbuilder.py
adaptivecardbuilder-0.0.9.data/data/LICENSE.txt
adaptivecardbuilder-0.0.9.dist-info/LICENSE.txt
adaptivecardbuilder-0.0.9.dist-info/METADATA
adaptivecardbuilder-0.0.9.dist-info/WHEEL
adaptivecardbuilder-0.0.9.dist-info/top_level.txt
adaptivecardbuilder-0.0.9.dist-info/RECORD
