Metadata-Version: 2.1
Name: adaptivecardbuilder
Version: 0.0.9
Summary: Easily Build and Export Multilingual Adaptive Cards Through Python
Home-page: https://github.com/ku222/AdaptiveCardBuilder
Author: Kovid Uppal
Author-email: kovid.uppal@gmail.com
License: UNKNOWN
Platform: UNKNOWN
Classifier: Programming Language :: Python :: 3
Classifier: Programming Language :: Python :: 3.6
Classifier: Programming Language :: Python :: 3.7
Classifier: Programming Language :: Python :: 3.8
Classifier: Programming Language :: Python :: 3.9
Classifier: License :: OSI Approved :: MIT License
Classifier: Operating System :: OS Independent
Classifier: Development Status :: 1 - Planning
Requires-Dist: aiohttp
